yagrc/dump.py
yagrc/importer.py
yagrc/reflector.py
yagrc-1.1.2.dist-info/LICENSE
yagrc-1.1.2.dist-info/METADATA
yagrc-1.1.2.dist-info/WHEEL
yagrc-1.1.2.dist-info/top_level.txt
yagrc-1.1.2.dist-info/RECORD
