Metadata-Version: 2.1
Name: yagrc
Version: 1.1.2
Summary: Yet another gRPC reflection client
Home-page: https://github.com/sparky8512/yagrc
Author-email: sparky8512-py@yahoo.com
License: Apache License 2.0
Classifier: Development Status :: 3 - Alpha
Classifier: Intended Audience :: Developers
Classifier: License :: OSI Approved :: Apache Software License
Classifier: Operating System :: OS Independent
Classifier: Programming Language :: Python :: 3
Classifier: Topic :: Software Development :: Libraries :: Python Modules
Requires-Python: >=3.7
License-File: LICENSE
Requires-Dist: grpcio (>=1.12.0)
Requires-Dist: grpcio-reflection (>=1.7.3)
Requires-Dist: protobuf (>=4.22.0)
Provides-Extra: test
Requires-Dist: pytest ; extra == 'test'
Requires-Dist: pytest-grpc ; extra == 'test'
